pyaqsapi/__init__.py
pyaqsapi/helperfunctions.py
pyaqsapi/listfunctions.py
pyaqsapi/metadatafunctions.py
pyaqsapi/setupfunctions.py
pyaqsapi/bybox/__init__.py
pyaqsapi/bybox/bybox.py
pyaqsapi/bycbsa/__init__.py
pyaqsapi/bycbsa/bycbsa.py
pyaqsapi/bycounty/__init__.py
pyaqsapi/bycounty/bycounty.py
pyaqsapi/byma/__init__.py
pyaqsapi/byma/byma.py
pyaqsapi/bypqao/__init__.py
pyaqsapi/bypqao/bypqao.py
pyaqsapi/bysite/__init__.py
pyaqsapi/bysite/bysite.py
pyaqsapi/bystate/__init__.py
pyaqsapi/bystate/bystate.py
pyaqsapi-1.0.1.dist-info/licenses/LICENSE.rst
pyaqsapi-1.0.1.dist-info/METADATA
pyaqsapi-1.0.1.dist-info/WHEEL
pyaqsapi-1.0.1.dist-info/top_level.txt
pyaqsapi-1.0.1.dist-info/RECORD
