Metadata-Version: 2.4
Name: pyaqsapi
Version: 1.0.1
Summary: United States Environmental Protection Agency (US EPA) Air Quality System (AQS) Data Mart API v2 interface.
Author-email: Clinton Mccrowey <mccrowey.clinton@epa.gov>
Maintainer-email: Clinton Mccrowey <mccrowey.clinton@epa.gov>
Project-URL: Homepage, https://github.com/USEPA/pyaqsapi
Project-URL: AQS, https://www.epa.gov/aqs
Project-URL: AQS DataMart, https://aqs.epa.gov/aqsweb/documents/data_mart_welcome.html
Project-URL: AQS Data Mart API, https://aqs.epa.gov/aqsweb/documents/data_api.html
Project-URL: pyaqsapi API Documentation, https://usepa.github.io/pyaqsapi/
Project-URL: SOURCE, https://github.com/USEPA/pyaqsapi.git
Project-URL: RAQSAPI, https://github.com/USEPA/RAQSAPI
Project-URL: Issue Tracker, https://github.com/USEPA/pyaqsapi/issues
Classifier: Development Status :: 4 - Beta
Classifier: Programming Language :: Python :: 3
Classifier: Operating System :: OS Independent
Requires-Python: >=3.9
License-File: LICENSE.rst
Dynamic: license-file
